weatherlink_v2_api_sdk/__init__.py
weatherlink_v2_api_sdk/signature/__init__.py
weatherlink_v2_api_sdk/signature/signature_calculator.py
weatherlink_v2_api_sdk-1.0.0.dist-info/LICENSE
weatherlink_v2_api_sdk-1.0.0.dist-info/METADATA
weatherlink_v2_api_sdk-1.0.0.dist-info/WHEEL
weatherlink_v2_api_sdk-1.0.0.dist-info/top_level.txt
weatherlink_v2_api_sdk-1.0.0.dist-info/RECORD
