Metadata-Version: 2.1
Name: weatherlink-v2-api-sdk
Version: 1.0.0
Summary: WeatherLink v2 API SDK for Python
Home-page: https://github.com/weatherlink/weatherlink-v2-api-sdk-python
Author: Jeremy Wall
Author-email: jeremyw@davisinstruments.com
License: Apache License 2.0
Project-URL: Bug Tracker, https://github.com/weatherlink/weatherlink-v2-api-sdk-python/issues
Platform: UNKNOWN
Classifier: Programming Language :: Python :: 3
Classifier: License :: OSI Approved :: Apache Software License
Classifier: Operating System :: OS Independent
Requires-Python: >=3.0
License-File: LICENSE
